Modion/THIS/__init__.py
Modion/THIS/placeholder.py
modion_this-0.0.1.dist-info/LICENSE
modion_this-0.0.1.dist-info/METADATA
modion_this-0.0.1.dist-info/WHEEL
modion_this-0.0.1.dist-info/top_level.txt
modion_this-0.0.1.dist-info/RECORD
